molskaten/__init__.py
molskaten/molskaten.py
molskaten/utils.py
molskaten-1.0.2.dist-info/LICENSE.md
molskaten-1.0.2.dist-info/WHEEL
molskaten-1.0.2.dist-info/METADATA
molskaten-1.0.2.dist-info/RECORD
